odoo/addons/product_configurator_sale_mrp/README.rst
odoo/addons/product_configurator_sale_mrp/__init__.py
odoo/addons/product_configurator_sale_mrp/__manifest__.py
odoo/addons/product_configurator_sale_mrp/i18n/product_configurator_sale_mrp.pot
odoo/addons/product_configurator_sale_mrp/models/__init__.py
odoo/addons/product_configurator_sale_mrp/models/procurement.py
odoo/addons/product_configurator_sale_mrp/models/sale.py
odoo/addons/product_configurator_sale_mrp/readme/DESCRIPTION.rst
odoo/addons/product_configurator_sale_mrp/static/description/icon.png
odoo/addons/product_configurator_sale_mrp/static/description/index.html
odoo/addons/product_configurator_sale_mrp/tests/__init__.py
odoo/addons/product_configurator_sale_mrp/tests/test_wizard.py
odoo/addons/product_configurator_sale_mrp/wizard/__init__.py
odoo/addons/product_configurator_sale_mrp/wizard/product_configurator.py
odoo14_addon_product_configurator_sale_mrp-14.0.1.0.2.dist-info/METADATA
odoo14_addon_product_configurator_sale_mrp-14.0.1.0.2.dist-info/WHEEL
odoo14_addon_product_configurator_sale_mrp-14.0.1.0.2.dist-info/top_level.txt
odoo14_addon_product_configurator_sale_mrp-14.0.1.0.2.dist-info/RECORD
